[
  {
    "inputs": [],
    "name": "InvalidInitialization",
    "type": "error"
  },
  {
    "inputs": [],
    "name": "NotInitializing",
    "type": "error"
  },
  {
    "inputs": [],
    "name": "ReentrancyGuardReentrantCall",
    "type": "error"
  },
  {
    "anonymous": false,
    "inputs": [
      {
        "indexed": true,
        "internalType": "uint256",
        "name": "campaignId",
        "type": "uint256"
      },
      {
        "indexed": true,
        "internalType": "address",
        "name": "newAdmin",
        "type": "address"
      },
      {
        "indexed": true,
        "internalType": "address",
        "name": "addedBy",
        "type": "address"
      }
    ],
    "name": "CampaignAdminAdded",
    "type": "event"
  },
  {
    "anonymous": false,
    "inputs": [
      {
        "indexed": true,
        "internalType": "uint256",
        "name": "campaignId",
        "type": "uint256"
      },
      {
        "indexed": true,
        "internalType": "address",
        "name": "admin",
        "type": "address"
      },
      {
        "indexed": true,
        "internalType": "address",
        "name": "removedBy",
        "type": "address"
      }
    ],
    "name": "CampaignAdminRemoved",
    "type": "event"
  },
  {
    "anonymous": false,
    "inputs": [
      {
        "indexed": true,
        "internalType": "uint256",
        "name": "campaignId",
        "type": "uint256"
      },
      {
        "indexed": true,
        "internalType": "address",
        "name": "admin",
        "type": "address"
      },
      {
        "indexed": false,
        "internalType": "string",
        "name": "name",
        "type": "string"
      },
      {
        "indexed": false,
        "internalType": "uint256",
        "name": "startTime",
        "type": "uint256"
      },
      {
        "indexed": false,
        "internalType": "uint256",
        "name": "endTime",
        "type": "uint256"
      }
    ],
    "name": "CampaignCreated",
    "type": "event"
  },
  {
    "anonymous": false,
    "inputs": [
      {
        "indexed": true,
        "internalType": "uint256",
        "name": "campaignId",
        "type": "uint256"
      },
      {
        "indexed": false,
        "internalType": "bool",
        "name": "featured",
        "type": "bool"
      },
      {
        "indexed": true,
        "internalType": "address",
        "name": "updatedBy",
        "type": "address"
      }
    ],
    "name": "CampaignFeatured",
    "type": "event"
  },
  {
    "anonymous": false,
    "inputs": [
      {
        "indexed": true,
        "internalType": "uint256",
        "name": "campaignId",
        "type": "uint256"
      },
      {
        "indexed": true,
        "internalType": "address",
        "name": "funder",
        "type": "address"
      },
      {
        "indexed": true,
        "internalType": "address",
        "name": "token",
        "type": "address"
      },
      {
        "indexed": false,
        "internalType": "uint256",
        "name": "amount",
        "type": "uint256"
      }
    ],
    "name": "CampaignFunded",
    "type": "event"
  },
  {
    "anonymous": false,
    "inputs": [
      {
        "indexed": true,
        "internalType": "uint256",
        "name": "campaignId",
        "type": "uint256"
      },
      {
        "indexed": false,
        "internalType": "uint256[]",
        "name": "projectIds",
        "type": "uint256[]"
      },
      {
        "indexed": false,
        "internalType": "uint256[]",
        "name": "amounts",
        "type": "uint256[]"
      },
      {
        "indexed": false,
        "internalType": "address",
        "name": "token",
        "type": "address"
      }
    ],
    "name": "CampaignFundsDistributed",
    "type": "event"
  },
  {
    "anonymous": false,
    "inputs": [
      {
        "indexed": true,
        "internalType": "uint256",
        "name": "campaignId",
        "type": "uint256"
      },
      {
        "indexed": true,
        "internalType": "address",
        "name": "withdrawer",
        "type": "address"
      },
      {
        "indexed": true,
        "internalType": "address",
        "name": "token",
        "type": "address"
      },
      {
        "indexed": false,
        "internalType": "uint256",
        "name": "amount",
        "type": "uint256"
      }
    ],
    "name": "CampaignFundsWithdrawn",
    "type": "event"
  },
  {
    "anonymous": false,
    "inputs": [
      {
        "indexed": true,
        "internalType": "uint256",
        "name": "campaignId",
        "type": "uint256"
      },
      {
        "indexed": true,
        "internalType": "address",
        "name": "updatedBy",
        "type": "address"
      }
    ],
    "name": "CampaignMetadataUpdated",
    "type": "event"
  },
  {
    "anonymous": false,
    "inputs": [
      {
        "indexed": true,
        "internalType": "uint256",
        "name": "campaignId",
        "type": "uint256"
      },
      {
        "indexed": false,
        "internalType": "enum OfficialStatus",
        "name": "oldStatus",
        "type": "uint8"
      },
      {
        "indexed": false,
        "internalType": "enum OfficialStatus",
        "name": "newStatus",
        "type": "uint8"
      },
      {
        "indexed": true,
        "internalType": "address",
        "name": "updatedBy",
        "type": "address"
      },
      {
        "indexed": false,
        "internalType": "string",
        "name": "reason",
        "type": "string"
      }
    ],
    "name": "CampaignStatusUpdated",
    "type": "event"
  },
  {
    "anonymous": false,
    "inputs": [
      {
        "indexed": true,
        "internalType": "uint256",
        "name": "campaignId",
        "type": "uint256"
      },
      {
        "indexed": false,
        "internalType": "string",
        "name": "tag",
        "type": "string"
      }
    ],
    "name": "CampaignTagAdded",
    "type": "event"
  },
  {
    "anonymous": false,
    "inputs": [
      {
        "indexed": true,
        "internalType": "uint256",
        "name": "campaignId",
        "type": "uint256"
      },
      {
        "indexed": false,
        "internalType": "string",
        "name": "tag",
        "type": "string"
      }
    ],
    "name": "CampaignTagRemoved",
    "type": "event"
  },
  {
    "anonymous": false,
    "inputs": [
      {
        "indexed": true,
        "internalType": "uint256",
        "name": "campaignId",
        "type": "uint256"
      },
      {
        "indexed": true,
        "internalType": "address",
        "name": "token",
        "type": "address"
      },
      {
        "indexed": false,
        "internalType": "uint256",
        "name": "oldWeight",
        "type": "uint256"
      },
      {
        "indexed": false,
        "internalType": "uint256",
        "name": "newWeight",
        "type": "uint256"
      },
      {
        "indexed": true,
        "internalType": "address",
        "name": "updatedBy",
        "type": "address"
      }
    ],
    "name": "CampaignTokenWeightUpdated",
    "type": "event"
  },
  {
    "anonymous": false,
    "inputs": [
      {
        "indexed": true,
        "internalType": "uint256",
        "name": "campaignId",
        "type": "uint256"
      },
      {
        "indexed": false,
        "internalType": "address[]",
        "name": "tokens",
        "type": "address[]"
      },
      {
        "indexed": false,
        "internalType": "uint256[]",
        "name": "weights",
        "type": "uint256[]"
      },
      {
        "indexed": true,
        "internalType": "address",
        "name": "updatedBy",
        "type": "address"
      }
    ],
    "name": "CampaignTokensUpdated",
    "type": "event"
  },
  {
    "anonymous": false,
    "inputs": [
      {
        "indexed": true,
        "internalType": "uint256",
        "name": "campaignId",
        "type": "uint256"
      },
      {
        "indexed": false,
        "internalType": "enum CampaignType",
        "name": "oldType",
        "type": "uint8"
      },
      {
        "indexed": false,
        "internalType": "enum CampaignType",
        "name": "newType",
        "type": "uint8"
      },
      {
        "indexed": true,
        "internalType": "address",
        "name": "updatedBy",
        "type": "address"
      }
    ],
    "name": "CampaignTypeUpdated",
    "type": "event"
  },
  {
    "anonymous": false,
    "inputs": [
      {
        "indexed": true,
        "internalType": "uint256",
        "name": "campaignId",
        "type": "uint256"
      },
      {
        "indexed": true,
        "internalType": "address",
        "name": "updatedBy",
        "type": "address"
      }
    ],
    "name": "CampaignUpdated",
    "type": "event"
  },
  {
    "anonymous": false,
    "inputs": [
      {
        "indexed": false,
        "internalType": "uint64",
        "name": "version",
        "type": "uint64"
      }
    ],
    "name": "Initialized",
    "type": "event"
  },
  {
    "anonymous": false,
    "inputs": [
      {
        "indexed": true,
        "internalType": "uint256",
        "name": "campaignId",
        "type": "uint256"
      },
      {
        "indexed": true,
        "internalType": "address",
        "name": "oldToken",
        "type": "address"
      },
      {
        "indexed": true,
        "internalType": "address",
        "name": "newToken",
        "type": "address"
      },
      {
        "indexed": false,
        "internalType": "uint256",
        "name": "oldAmount",
        "type": "uint256"
      },
      {
        "indexed": false,
        "internalType": "uint256",
        "name": "newAmount",
        "type": "uint256"
      },
      {
        "indexed": false,
        "internalType": "address",
        "name": "updatedBy",
        "type": "address"
      }
    ],
    "name": "ProjectAdditionFeeUpdated",
    "type": "event"
  },
  {
    "anonymous": false,
    "inputs": [
      {
        "indexed": true,
        "internalType": "uint256",
        "name": "campaignId",
        "type": "uint256"
      },
      {
        "indexed": true,
        "internalType": "address",
        "name": "user",
        "type": "address"
      },
      {
        "indexed": false,
        "internalType": "uint256",
        "name": "maxAmount",
        "type": "uint256"
      }
    ],
    "name": "UserMaxVoteAmountSet",
    "type": "event"
  },
  {
    "inputs": [],
    "name": "ADMIN_ROLE",
    "outputs": [
      {
        "internalType": "bytes32",
        "name": "",
        "type": "bytes32"
      }
    ],
    "stateMutability": "view",
    "type": "function"
  },
  {
    "inputs": [],
    "name": "MANAGER_ROLE",
    "outputs": [
      {
        "internalType": "bytes32",
        "name": "",
        "type": "bytes32"
      }
    ],
    "stateMutability": "view",
    "type": "function"
  },
  {
    "inputs": [
      {
        "internalType": "uint256",
        "name": "_campaignId",
        "type": "uint256"
      },
      {
        "internalType": "address",
        "name": "_newAdmin",
        "type": "address"
      }
    ],
    "name": "addCampaignAdmin",
    "outputs": [],
    "stateMutability": "nonpayable",
    "type": "function"
  },
  {
    "inputs": [
      {
        "internalType": "uint256",
        "name": "_campaignId",
        "type": "uint256"
      },
      {
        "internalType": "string",
        "name": "_tag",
        "type": "string"
      }
    ],
    "name": "addCampaignTag",
    "outputs": [],
    "stateMutability": "nonpayable",
    "type": "function"
  },
  {
    "inputs": [
      {
        "internalType": "address",
        "name": "",
        "type": "address"
      },
      {
        "internalType": "uint256",
        "name": "",
        "type": "uint256"
      }
    ],
    "name": "adminCampaigns",
    "outputs": [
      {
        "internalType": "uint256",
        "name": "",
        "type": "uint256"
      }
    ],
    "stateMutability": "view",
    "type": "function"
  },
  {
    "inputs": [
      {
        "internalType": "uint256[]",
        "name": "_campaignIds",
        "type": "uint256[]"
      },
      {
        "internalType": "enum OfficialStatus",
        "name": "_newStatus",
        "type": "uint8"
      },
      {
        "internalType": "string",
        "name": "_reason",
        "type": "string"
      }
    ],
    "name": "batchUpdateCampaignStatus",
    "outputs": [],
    "stateMutability": "nonpayable",
    "type": "function"
  },
  {
    "inputs": [
      {
        "internalType": "uint256",
        "name": "",
        "type": "uint256"
      },
      {
        "internalType": "string",
        "name": "",
        "type": "string"
      }
    ],
    "name": "campaignHasTag",
    "outputs": [
      {
        "internalType": "bool",
        "name": "",
        "type": "bool"
      }
    ],
    "stateMutability": "view",
    "type": "function"
  },
  {
    "inputs": [
      {
        "internalType": "uint256",
        "name": "",
        "type": "uint256"
      }
    ],
    "name": "campaignIds",
    "outputs": [
      {
        "internalType": "uint256",
        "name": "",
        "type": "uint256"
      }
    ],
    "stateMutability": "view",
    "type": "function"
  },
  {
    "inputs": [
      {
        "internalType": "uint256",
        "name": "",
        "type": "uint256"
      }
    ],
    "name": "campaigns",
    "outputs": [
      {
        "internalType": "uint256",
        "name": "id",
        "type": "uint256"
      },
      {
        "internalType": "address",
        "name": "admin",
        "type": "address"
      },
      {
        "internalType": "string",
        "name": "name",
        "type": "string"
      },
      {
        "internalType": "string",
        "name": "description",
        "type": "string"
      },
      {
        "internalType": "uint256",
        "name": "startTime",
        "type": "uint256"
      },
      {
        "internalType": "uint256",
        "name": "endTime",
        "type": "uint256"
      },
      {
        "internalType": "bool",
        "name": "active",
        "type": "bool"
      },
      {
        "internalType": "uint256",
        "name": "totalFunds",
        "type": "uint256"
      },
      {
        "internalType": "uint256",
        "name": "createdAt",
        "type": "uint256"
      },
      {
        "internalType": "uint256",
        "name": "lastUpdated",
        "type": "uint256"
      },
      {
        "internalType": "string",
        "name": "mainInfo",
        "type": "string"
      },
      {
        "internalType": "string",
        "name": "additionalInfo",
        "type": "string"
      },
      {
        "internalType": "uint256",
        "name": "adminFeePercentage",
        "type": "uint256"
      },
      {
        "internalType": "uint256",
        "name": "maxWinners",
        "type": "uint256"
      },
      {
        "internalType": "bool",
        "name": "useQuadraticDistribution",
        "type": "bool"
      },
      {
        "internalType": "bool",
        "name": "useCustomDistribution",
        "type": "bool"
      },
      {
        "internalType": "string",
        "name": "customDistributionData",
        "type": "string"
      },
      {
        "internalType": "address",
        "name": "payoutToken",
        "type": "address"
      },
      {
        "internalType": "enum OfficialStatus",
        "name": "officialStatus",
        "type": "uint8"
      },
      {
        "internalType": "bool",
        "name": "autoPoolCreated",
        "type": "bool"
      },
      {
        "internalType": "string",
        "name": "websiteUrl",
        "type": "string"
      },
      {
        "internalType": "string",
        "name": "socialMediaHandle",
        "type": "string"
      },
      {
        "internalType": "uint256",
        "name": "totalParticipants",
        "type": "uint256"
      },
      {
        "internalType": "uint256",
        "name": "totalProjects",
        "type": "uint256"
      },
      {
        "internalType": "bool",
        "name": "featuredCampaign",
        "type": "bool"
      },
      {
        "internalType": "uint256",
        "name": "minimumVoteAmount",
        "type": "uint256"
      },
      {
        "internalType": "uint256",
        "name": "maximumVoteAmount",
        "type": "uint256"
      },
      {
        "internalType": "enum CampaignType",
        "name": "campaignType",
        "type": "uint8"
      },
      {
        "internalType": "bool",
        "name": "isERC20Campaign",
        "type": "bool"
      },
      {
        "internalType": "address",
        "name": "projectAdditionFeeToken",
        "type": "address"
      },
      {
        "internalType": "uint256",
        "name": "projectAdditionFeeAmount",
        "type": "uint256"
      }
    ],
    "stateMutability": "view",
    "type": "function"
  },
  {
    "inputs": [
      {
        "internalType": "bool",
        "name": "",
        "type": "bool"
      },
      {
        "internalType": "uint256",
        "name": "",
        "type": "uint256"
      }
    ],
    "name": "campaignsByActiveStatus",
    "outputs": [
      {
        "internalType": "uint256",
        "name": "",
        "type": "uint256"
      }
    ],
    "stateMutability": "view",
    "type": "function"
  },
  {
    "inputs": [
      {
        "internalType": "uint256",
        "name": "",
        "type": "uint256"
      },
      {
        "internalType": "uint256",
        "name": "",
        "type": "uint256"
      }
    ],
    "name": "campaignsByMonth",
    "outputs": [
      {
        "internalType": "uint256",
        "name": "",
        "type": "uint256"
      }
    ],
    "stateMutability": "view",
    "type": "function"
  },
  {
    "inputs": [
      {
        "internalType": "enum OfficialStatus",
        "name": "",
        "type": "uint8"
      },
      {
        "internalType": "uint256",
        "name": "",
        "type": "uint256"
      }
    ],
    "name": "campaignsByStatus",
    "outputs": [
      {
        "internalType": "uint256",
        "name": "",
        "type": "uint256"
      }
    ],
    "stateMutability": "view",
    "type": "function"
  },
  {
    "inputs": [
      {
        "internalType": "string",
        "name": "",
        "type": "string"
      },
      {
        "internalType": "uint256",
        "name": "",
        "type": "uint256"
      }
    ],
    "name": "campaignsByTag",
    "outputs": [
      {
        "internalType": "uint256",
        "name": "",
        "type": "uint256"
      }
    ],
    "stateMutability": "view",
    "type": "function"
  },
  {
    "inputs": [
      {
        "internalType": "address",
        "name": "",
        "type": "address"
      },
      {
        "internalType": "uint256",
        "name": "",
        "type": "uint256"
      }
    ],
    "name": "campaignsByToken",
    "outputs": [
      {
        "internalType": "uint256",
        "name": "",
        "type": "uint256"
      }
    ],
    "stateMutability": "view",
    "type": "function"
  },
  {
    "inputs": [
      {
        "internalType": "uint256",
        "name": "",
        "type": "uint256"
      },
      {
        "internalType": "uint256",
        "name": "",
        "type": "uint256"
      }
    ],
    "name": "campaignsByType",
    "outputs": [
      {
        "internalType": "uint256",
        "name": "",
        "type": "uint256"
      }
    ],
    "stateMutability": "view",
    "type": "function"
  },
  {
    "inputs": [
      {
        "internalType": "string",
        "name": "_name",
        "type": "string"
      },
      {
        "internalType": "string",
        "name": "_description",
        "type": "string"
      },
      {
        "internalType": "string",
        "name": "_mainInfo",
        "type": "string"
      },
      {
        "internalType": "string",
        "name": "_additionalInfo",
        "type": "string"
      },
      {
        "internalType": "uint256",
        "name": "_startTime",
        "type": "uint256"
      },
      {
        "internalType": "uint256",
        "name": "_endTime",
        "type": "uint256"
      },
      {
        "internalType": "uint256",
        "name": "_adminFeePercentage",
        "type": "uint256"
      },
      {
        "internalType": "uint256",
        "name": "_maxWinners",
        "type": "uint256"
      },
      {
        "internalType": "bool",
        "name": "_useQuadraticDistribution",
        "type": "bool"
      },
      {
        "internalType": "bool",
        "name": "_useCustomDistribution",
        "type": "bool"
      },
      {
        "internalType": "string",
        "name": "_customDistributionData",
        "type": "string"
      },
      {
        "internalType": "address",
        "name": "_payoutToken",
        "type": "address"
      }
    ],
    "name": "createCampaign",
    "outputs": [
      {
        "internalType": "uint256",
        "name": "",
        "type": "uint256"
      }
    ],
    "stateMutability": "nonpayable",
    "type": "function"
  },
  {
    "inputs": [
      {
        "internalType": "uint256",
        "name": "_v4CampaignId",
        "type": "uint256"
      },
      {
        "internalType": "address",
        "name": "_admin",
        "type": "address"
      },
      {
        "internalType": "string",
        "name": "_name",
        "type": "string"
      },
      {
        "internalType": "string",
        "name": "_description",
        "type": "string"
      },
      {
        "internalType": "string",
        "name": "_mainInfo",
        "type": "string"
      },
      {
        "internalType": "string",
        "name": "_additionalInfo",
        "type": "string"
      },
      {
        "internalType": "uint256",
        "name": "_startTime",
        "type": "uint256"
      },
      {
        "internalType": "uint256",
        "name": "_endTime",
        "type": "uint256"
      },
      {
        "internalType": "uint256",
        "name": "_adminFeePercentage",
        "type": "uint256"
      },
      {
        "internalType": "uint256",
        "name": "_maxWinners",
        "type": "uint256"
      },
      {
        "internalType": "bool",
        "name": "_useQuadraticDistribution",
        "type": "bool"
      },
      {
        "internalType": "bool",
        "name": "_useCustomDistribution",
        "type": "bool"
      },
      {
        "internalType": "string",
        "name": "_customDistributionData",
        "type": "string"
      },
      {
        "internalType": "address",
        "name": "_payoutToken",
        "type": "address"
      },
      {
        "internalType": "bool",
        "name": "_active",
        "type": "bool"
      },
      {
        "internalType": "uint256",
        "name": "_totalFunds",
        "type": "uint256"
      },
      {
        "internalType": "uint256",
        "name": "_createdAt",
        "type": "uint256"
      }
    ],
    "name": "createCampaignFromV4",
    "outputs": [
      {
        "internalType": "uint256",
        "name": "",
        "type": "uint256"
      }
    ],
    "stateMutability": "nonpayable",
    "type": "function"
  },
  {
    "inputs": [
      {
        "internalType": "string",
        "name": "_name",
        "type": "string"
      },
      {
        "internalType": "string",
        "name": "_description",
        "type": "string"
      },
      {
        "internalType": "uint256",
        "name": "_startTime",
        "type": "uint256"
      },
      {
        "internalType": "uint256",
        "name": "_endTime",
        "type": "uint256"
      },
      {
        "internalType": "string",
        "name": "_mainInfo",
        "type": "string"
      },
      {
        "internalType": "string",
        "name": "_additionalInfo",
        "type": "string"
      },
      {
        "internalType": "uint256",
        "name": "_adminFeePercentage",
        "type": "uint256"
      },
      {
        "internalType": "uint256",
        "name": "_maxWinners",
        "type": "uint256"
      },
      {
        "internalType": "bool",
        "name": "_useQuadraticDistribution",
        "type": "bool"
      },
      {
        "internalType": "bool",
        "name": "_useCustomDistribution",
        "type": "bool"
      },
      {
        "internalType": "string",
        "name": "_customDistributionData",
        "type": "string"
      },
      {
        "internalType": "address",
        "name": "_payoutToken",
        "type": "address"
      }
    ],
    "name": "createCampaignV4",
    "outputs": [
      {
        "internalType": "uint256",
        "name": "",
        "type": "uint256"
      }
    ],
    "stateMutability": "nonpayable",
    "type": "function"
  },
  {
    "inputs": [
      {
        "internalType": "string",
        "name": "_name",
        "type": "string"
      },
      {
        "internalType": "string",
        "name": "_description",
        "type": "string"
      },
      {
        "internalType": "string",
        "name": "_mainInfo",
        "type": "string"
      },
      {
        "internalType": "string",
        "name": "_additionalInfo",
        "type": "string"
      },
      {
        "internalType": "uint256",
        "name": "_startTime",
        "type": "uint256"
      },
      {
        "internalType": "uint256",
        "name": "_endTime",
        "type": "uint256"
      },
      {
        "internalType": "uint256",
        "name": "_adminFeePercentage",
        "type": "uint256"
      },
      {
        "internalType": "uint256",
        "name": "_maxWinners",
        "type": "uint256"
      },
      {
        "internalType": "bool",
        "name": "_useQuadraticDistribution",
        "type": "bool"
      },
      {
        "internalType": "bool",
        "name": "_useCustomDistribution",
        "type": "bool"
      },
      {
        "internalType": "string",
        "name": "_customDistributionData",
        "type": "string"
      },
      {
        "internalType": "address",
        "name": "_payoutToken",
        "type": "address"
      },
      {
        "internalType": "enum CampaignType",
        "name": "_campaignType",
        "type": "uint8"
      },
      {
        "internalType": "address[]",
        "name": "_allowedTokens",
        "type": "address[]"
      },
      {
        "internalType": "uint256[]",
        "name": "_tokenWeights",
        "type": "uint256[]"
      },
      {
        "internalType": "address",
        "name": "_projectAdditionFeeToken",
        "type": "address"
      },
      {
        "internalType": "uint256",
        "name": "_projectAdditionFeeAmount",
        "type": "uint256"
      }
    ],
    "name": "createERC20Campaign",
    "outputs": [
      {
        "internalType": "uint256",
        "name": "",
        "type": "uint256"
      }
    ],
    "stateMutability": "nonpayable",
    "type": "function"
  },
  {
    "inputs": [
      {
        "internalType": "uint256",
        "name": "_campaignId",
        "type": "uint256"
      }
    ],
    "name": "deactivateCampaign",
    "outputs": [],
    "stateMutability": "nonpayable",
    "type": "function"
  },
  {
    "inputs": [
      {
        "internalType": "uint256",
        "name": "_campaignId",
        "type": "uint256"
      },
      {
        "internalType": "string",
        "name": "_newDescription",
        "type": "string"
      }
    ],
    "name": "editCampaignDescription",
    "outputs": [],
    "stateMutability": "nonpayable",
    "type": "function"
  },
  {
    "inputs": [
      {
        "internalType": "uint256",
        "name": "_campaignId",
        "type": "uint256"
      },
      {
        "internalType": "uint256",
        "name": "_newEndTime",
        "type": "uint256"
      }
    ],
    "name": "editCampaignEndTime",
    "outputs": [],
    "stateMutability": "nonpayable",
    "type": "function"
  },
  {
    "inputs": [
      {
        "internalType": "uint256",
        "name": "_campaignId",
        "type": "uint256"
      },
      {
        "internalType": "string",
        "name": "_newName",
        "type": "string"
      }
    ],
    "name": "editCampaignName",
    "outputs": [],
    "stateMutability": "nonpayable",
    "type": "function"
  },
  {
    "inputs": [
      {
        "internalType": "uint256",
        "name": "_campaignId",
        "type": "uint256"
      },
      {
        "internalType": "address",
        "name": "_token",
        "type": "address"
      },
      {
        "internalType": "uint256",
        "name": "_amount",
        "type": "uint256"
      }
    ],
    "name": "fundCampaign",
    "outputs": [],
    "stateMutability": "nonpayable",
    "type": "function"
  },
  {
    "inputs": [],
    "name": "getActiveCampaigns",
    "outputs": [
      {
        "internalType": "uint256[]",
        "name": "",
        "type": "uint256[]"
      }
    ],
    "stateMutability": "view",
    "type": "function"
  },
  {
    "inputs": [],
    "name": "getAllCampaignIds",
    "outputs": [
      {
        "internalType": "uint256[]",
        "name": "",
        "type": "uint256[]"
      }
    ],
    "stateMutability": "view",
    "type": "function"
  },
  {
    "inputs": [
      {
        "internalType": "uint256",
        "name": "_campaignId",
        "type": "uint256"
      }
    ],
    "name": "getCampaign",
    "outputs": [
      {
        "internalType": "uint256",
        "name": "id",
        "type": "uint256"
      },
      {
        "internalType": "address",
        "name": "admin",
        "type": "address"
      },
      {
        "internalType": "string",
        "name": "name",
        "type": "string"
      },
      {
        "internalType": "string",
        "name": "description",
        "type": "string"
      },
      {
        "internalType": "uint256",
        "name": "startTime",
        "type": "uint256"
      },
      {
        "internalType": "uint256",
        "name": "endTime",
        "type": "uint256"
      },
      {
        "internalType": "uint256",
        "name": "adminFeePercentage",
        "type": "uint256"
      },
      {
        "internalType": "uint256",
        "name": "maxWinners",
        "type": "uint256"
      },
      {
        "internalType": "bool",
        "name": "useQuadraticDistribution",
        "type": "bool"
      },
      {
        "internalType": "bool",
        "name": "useCustomDistribution",
        "type": "bool"
      },
      {
        "internalType": "address",
        "name": "payoutToken",
        "type": "address"
      },
      {
        "internalType": "bool",
        "name": "active",
        "type": "bool"
      },
      {
        "internalType": "uint256",
        "name": "totalFunds",
        "type": "uint256"
      }
    ],
    "stateMutability": "view",
    "type": "function"
  },
  {
    "inputs": [
      {
        "internalType": "uint256",
        "name": "_campaignId",
        "type": "uint256"
      }
    ],
    "name": "getCampaignAdmins",
    "outputs": [
      {
        "internalType": "address[]",
        "name": "",
        "type": "address[]"
      }
    ],
    "stateMutability": "view",
    "type": "function"
  },
  {
    "inputs": [
      {
        "internalType": "uint256",
        "name": "_campaignId",
        "type": "uint256"
      }
    ],
    "name": "getCampaignAnalytics",
    "outputs": [
      {
        "internalType": "uint256",
        "name": "totalFunds",
        "type": "uint256"
      },
      {
        "internalType": "uint256",
        "name": "totalParticipants",
        "type": "uint256"
      },
      {
        "internalType": "uint256",
        "name": "totalProjects",
        "type": "uint256"
      },
      {
        "internalType": "uint256",
        "name": "totalTokenTypes",
        "type": "uint256"
      },
      {
        "internalType": "uint256",
        "name": "daysRemaining",
        "type": "uint256"
      },
      {
        "internalType": "bool",
        "name": "isActive",
        "type": "bool"
      },
      {
        "internalType": "bool",
        "name": "hasEnded",
        "type": "bool"
      }
    ],
    "stateMutability": "view",
    "type": "function"
  },
  {
    "inputs": [],
    "name": "getCampaignCount",
    "outputs": [
      {
        "internalType": "uint256",
        "name": "",
        "type": "uint256"
      }
    ],
    "stateMutability": "view",
    "type": "function"
  },
  {
    "inputs": [
      {
        "internalType": "uint256",
        "name": "_campaignId",
        "type": "uint256"
      }
    ],
    "name": "getCampaignEnhancedInfo",
    "outputs": [
      {
        "internalType": "enum OfficialStatus",
        "name": "officialStatus",
        "type": "uint8"
      },
      {
        "internalType": "string",
        "name": "websiteUrl",
        "type": "string"
      },
      {
        "internalType": "string",
        "name": "socialMediaHandle",
        "type": "string"
      },
      {
        "internalType": "string[]",
        "name": "tags",
        "type": "string[]"
      },
      {
        "internalType": "uint256",
        "name": "totalParticipants",
        "type": "uint256"
      },
      {
        "internalType": "uint256",
        "name": "totalProjects",
        "type": "uint256"
      },
      {
        "internalType": "bool",
        "name": "featuredCampaign",
        "type": "bool"
      },
      {
        "internalType": "uint256",
        "name": "minimumVoteAmount",
        "type": "uint256"
      },
      {
        "internalType": "uint256",
        "name": "maximumVoteAmount",
        "type": "uint256"
      },
      {
        "internalType": "uint256",
        "name": "lastUpdated",
        "type": "uint256"
      }
    ],
    "stateMutability": "view",
    "type": "function"
  },
  {
    "inputs": [
      {
        "internalType": "uint256",
        "name": "_campaignId",
        "type": "uint256"
      }
    ],
    "name": "getCampaignMetadata",
    "outputs": [
      {
        "internalType": "string",
        "name": "mainInfo",
        "type": "string"
      },
      {
        "internalType": "string",
        "name": "additionalInfo",
        "type": "string"
      },
      {
        "internalType": "string",
        "name": "customDistributionData",
        "type": "string"
      }
    ],
    "stateMutability": "view",
    "type": "function"
  },
  {
    "inputs": [
      {
        "internalType": "uint256",
        "name": "_campaignId",
        "type": "uint256"
      },
      {
        "internalType": "address",
        "name": "_token",
        "type": "address"
      }
    ],
    "name": "getCampaignTokenAmount",
    "outputs": [
      {
        "internalType": "uint256",
        "name": "",
        "type": "uint256"
      }
    ],
    "stateMutability": "view",
    "type": "function"
  },
  {
    "inputs": [
      {
        "internalType": "uint256",
        "name": "_campaignId",
        "type": "uint256"
      }
    ],
    "name": "getCampaignVotedTokens",
    "outputs": [
      {
        "internalType": "address[]",
        "name": "",
        "type": "address[]"
      }
    ],
    "stateMutability": "view",
    "type": "function"
  },
  {
    "inputs": [
      {
        "internalType": "uint256",
        "name": "_campaignId",
        "type": "uint256"
      }
    ],
    "name": "getCampaignWithPoolStatus",
    "outputs": [
      {
        "internalType": "uint256",
        "name": "id",
        "type": "uint256"
      },
      {
        "internalType": "address",
        "name": "admin",
        "type": "address"
      },
      {
        "internalType": "string",
        "name": "name",
        "type": "string"
      },
      {
        "internalType": "string",
        "name": "description",
        "type": "string"
      },
      {
        "internalType": "uint256",
        "name": "startTime",
        "type": "uint256"
      },
      {
        "internalType": "uint256",
        "name": "endTime",
        "type": "uint256"
      },
      {
        "internalType": "uint256",
        "name": "adminFeePercentage",
        "type": "uint256"
      },
      {
        "internalType": "uint256",
        "name": "maxWinners",
        "type": "uint256"
      },
      {
        "internalType": "bool",
        "name": "useQuadraticDistribution",
        "type": "bool"
      },
      {
        "internalType": "bool",
        "name": "useCustomDistribution",
        "type": "bool"
      },
      {
        "internalType": "address",
        "name": "payoutToken",
        "type": "address"
      },
      {
        "internalType": "bool",
        "name": "active",
        "type": "bool"
      },
      {
        "internalType": "uint256",
        "name": "totalFunds",
        "type": "uint256"
      },
      {
        "internalType": "uint256",
        "name": "totalPools",
        "type": "uint256"
      },
      {
        "internalType": "uint256",
        "name": "poolTotalFunds",
        "type": "uint256"
      },
      {
        "internalType": "uint256",
        "name": "poolTotalVotes",
        "type": "uint256"
      },
      {
        "internalType": "bool",
        "name": "hasActivePools",
        "type": "bool"
      }
    ],
    "stateMutability": "nonpayable",
    "type": "function"
  },
  {
    "inputs": [
      {
        "internalType": "address",
        "name": "_admin",
        "type": "address"
      }
    ],
    "name": "getCampaignsByAdmin",
    "outputs": [
      {
        "internalType": "uint256[]",
        "name": "",
        "type": "uint256[]"
      }
    ],
    "stateMutability": "view",
    "type": "function"
  },
  {
    "inputs": [
      {
        "internalType": "uint256",
        "name": "_monthTimestamp",
        "type": "uint256"
      }
    ],
    "name": "getCampaignsByMonth",
    "outputs": [
      {
        "internalType": "uint256[]",
        "name": "",
        "type": "uint256[]"
      }
    ],
    "stateMutability": "view",
    "type": "function"
  },
  {
    "inputs": [
      {
        "internalType": "enum OfficialStatus",
        "name": "_status",
        "type": "uint8"
      }
    ],
    "name": "getCampaignsByStatus",
    "outputs": [
      {
        "internalType": "uint256[]",
        "name": "",
        "type": "uint256[]"
      }
    ],
    "stateMutability": "view",
    "type": "function"
  },
  {
    "inputs": [
      {
        "internalType": "string",
        "name": "_tag",
        "type": "string"
      }
    ],
    "name": "getCampaignsByTag",
    "outputs": [
      {
        "internalType": "uint256[]",
        "name": "",
        "type": "uint256[]"
      }
    ],
    "stateMutability": "view",
    "type": "function"
  },
  {
    "inputs": [
      {
        "internalType": "uint256",
        "name": "_startTime",
        "type": "uint256"
      },
      {
        "internalType": "uint256",
        "name": "_endTime",
        "type": "uint256"
      }
    ],
    "name": "getCampaignsByTimeRange",
    "outputs": [
      {
        "internalType": "uint256[]",
        "name": "",
        "type": "uint256[]"
      }
    ],
    "stateMutability": "view",
    "type": "function"
  },
  {
    "inputs": [
      {
        "internalType": "address",
        "name": "_token",
        "type": "address"
      }
    ],
    "name": "getCampaignsByToken",
    "outputs": [
      {
        "internalType": "uint256[]",
        "name": "",
        "type": "uint256[]"
      }
    ],
    "stateMutability": "view",
    "type": "function"
  },
  {
    "inputs": [
      {
        "internalType": "enum CampaignType",
        "name": "_type",
        "type": "uint8"
      }
    ],
    "name": "getCampaignsByType",
    "outputs": [
      {
        "internalType": "uint256[]",
        "name": "",
        "type": "uint256[]"
      }
    ],
    "stateMutability": "view",
    "type": "function"
  },
  {
    "inputs": [
      {
        "internalType": "uint256",
        "name": "_campaignId",
        "type": "uint256"
      }
    ],
    "name": "getERC20CampaignConfig",
    "outputs": [
      {
        "internalType": "enum CampaignType",
        "name": "campaignType",
        "type": "uint8"
      },
      {
        "internalType": "bool",
        "name": "isERC20Campaign",
        "type": "bool"
      },
      {
        "internalType": "address[]",
        "name": "allowedTokens",
        "type": "address[]"
      },
      {
        "internalType": "uint256[]",
        "name": "tokenWeights",
        "type": "uint256[]"
      },
      {
        "internalType": "address",
        "name": "projectAdditionFeeToken",
        "type": "address"
      },
      {
        "internalType": "uint256",
        "name": "projectAdditionFeeAmount",
        "type": "uint256"
      }
    ],
    "stateMutability": "view",
    "type": "function"
  },
  {
    "inputs": [],
    "name": "getFeaturedCampaigns",
    "outputs": [
      {
        "internalType": "uint256[]",
        "name": "",
        "type": "uint256[]"
      }
    ],
    "stateMutability": "view",
    "type": "function"
  },
  {
    "inputs": [],
    "name": "getInactiveCampaigns",
    "outputs": [
      {
        "internalType": "uint256[]",
        "name": "",
        "type": "uint256[]"
      }
    ],
    "stateMutability": "view",
    "type": "function"
  },
  {
    "inputs": [],
    "name": "getModuleName",
    "outputs": [
      {
        "internalType": "string",
        "name": "",
        "type": "string"
      }
    ],
    "stateMutability": "pure",
    "type": "function"
  },
  {
    "inputs": [],
    "name": "getModuleVersion",
    "outputs": [
      {
        "internalType": "uint256",
        "name": "",
        "type": "uint256"
      }
    ],
    "stateMutability": "pure",
    "type": "function"
  },
  {
    "inputs": [],
    "name": "getPlatformAnalytics",
    "outputs": [
      {
        "internalType": "uint256",
        "name": "totalCampaigns",
        "type": "uint256"
      },
      {
        "internalType": "uint256",
        "name": "activeCampaigns",
        "type": "uint256"
      },
      {
        "internalType": "uint256",
        "name": "totalFundsRaised",
        "type": "uint256"
      },
      {
        "internalType": "uint256",
        "name": "featuredCampaignsCount",
        "type": "uint256"
      }
    ],
    "stateMutability": "view",
    "type": "function"
  },
  {
    "inputs": [
      {
        "internalType": "uint256",
        "name": "_campaignId",
        "type": "uint256"
      }
    ],
    "name": "getProjectAdditionFeeConfig",
    "outputs": [
      {
        "internalType": "address",
        "name": "feeToken",
        "type": "address"
      },
      {
        "internalType": "uint256",
        "name": "feeAmount",
        "type": "uint256"
      }
    ],
    "stateMutability": "nonpayable",
    "type": "function"
  },
  {
    "inputs": [
      {
        "internalType": "uint256",
        "name": "_campaignId",
        "type": "uint256"
      },
      {
        "internalType": "address",
        "name": "_token",
        "type": "address"
      }
    ],
    "name": "getTokenWeight",
    "outputs": [
      {
        "internalType": "uint256",
        "name": "",
        "type": "uint256"
      }
    ],
    "stateMutability": "view",
    "type": "function"
  },
  {
    "inputs": [
      {
        "internalType": "uint256",
        "name": "_campaignId",
        "type": "uint256"
      },
      {
        "internalType": "address",
        "name": "_user",
        "type": "address"
      }
    ],
    "name": "getUserMaxVoteAmount",
    "outputs": [
      {
        "internalType": "uint256",
        "name": "",
        "type": "uint256"
      }
    ],
    "stateMutability": "view",
    "type": "function"
  },
  {
    "inputs": [
      {
        "internalType": "address",
        "name": "_main",
        "type": "address"
      }
    ],
    "name": "initialize",
    "outputs": [],
    "stateMutability": "nonpayable",
    "type": "function"
  },
  {
    "inputs": [
      {
        "internalType": "uint256",
        "name": "_campaignId",
        "type": "uint256"
      },
      {
        "internalType": "address",
        "name": "_admin",
        "type": "address"
      }
    ],
    "name": "isCampaignAdmin",
    "outputs": [
      {
        "internalType": "bool",
        "name": "",
        "type": "bool"
      }
    ],
    "stateMutability": "view",
    "type": "function"
  },
  {
    "inputs": [
      {
        "internalType": "uint256",
        "name": "_campaignId",
        "type": "uint256"
      },
      {
        "internalType": "address",
        "name": "_token",
        "type": "address"
      }
    ],
    "name": "isTokenAllowedForCampaign",
    "outputs": [
      {
        "internalType": "bool",
        "name": "",
        "type": "bool"
      }
    ],
    "stateMutability": "view",
    "type": "function"
  },
  {
    "inputs": [],
    "name": "mainContract",
    "outputs": [
      {
        "internalType": "contract ISovereignSeasV5",
        "name": "",
        "type": "address"
      }
    ],
    "stateMutability": "view",
    "type": "function"
  },
  {
    "inputs": [],
    "name": "nextCampaignId",
    "outputs": [
      {
        "internalType": "uint256",
        "name": "",
        "type": "uint256"
      }
    ],
    "stateMutability": "view",
    "type": "function"
  },
  {
    "inputs": [
      {
        "internalType": "uint256",
        "name": "_campaignId",
        "type": "uint256"
      }
    ],
    "name": "reactivateCampaign",
    "outputs": [],
    "stateMutability": "nonpayable",
    "type": "function"
  },
  {
    "inputs": [
      {
        "internalType": "uint256",
        "name": "_campaignId",
        "type": "uint256"
      },
      {
        "internalType": "address",
        "name": "_admin",
        "type": "address"
      }
    ],
    "name": "removeCampaignAdmin",
    "outputs": [],
    "stateMutability": "nonpayable",
    "type": "function"
  },
  {
    "inputs": [
      {
        "internalType": "uint256",
        "name": "_campaignId",
        "type": "uint256"
      },
      {
        "internalType": "string",
        "name": "_tag",
        "type": "string"
      }
    ],
    "name": "removeCampaignTag",
    "outputs": [],
    "stateMutability": "nonpayable",
    "type": "function"
  },
  {
    "inputs": [
      {
        "internalType": "string",
        "name": "_searchTerm",
        "type": "string"
      }
    ],
    "name": "searchCampaignsByName",
    "outputs": [
      {
        "internalType": "uint256[]",
        "name": "",
        "type": "uint256[]"
      }
    ],
    "stateMutability": "view",
    "type": "function"
  },
  {
    "inputs": [
      {
        "internalType": "uint256",
        "name": "_campaignId",
        "type": "uint256"
      },
      {
        "internalType": "address[]",
        "name": "_admins",
        "type": "address[]"
      }
    ],
    "name": "setCampaignAdminsFromV4",
    "outputs": [],
    "stateMutability": "nonpayable",
    "type": "function"
  },
  {
    "inputs": [
      {
        "internalType": "uint256",
        "name": "_campaignId",
        "type": "uint256"
      },
      {
        "internalType": "bool",
        "name": "_featured",
        "type": "bool"
      }
    ],
    "name": "setCampaignFeatured",
    "outputs": [],
    "stateMutability": "nonpayable",
    "type": "function"
  },
  {
    "inputs": [
      {
        "internalType": "uint256",
        "name": "_campaignId",
        "type": "uint256"
      },
      {
        "internalType": "string",
        "name": "_socialMediaHandle",
        "type": "string"
      }
    ],
    "name": "setCampaignSocialMedia",
    "outputs": [],
    "stateMutability": "nonpayable",
    "type": "function"
  },
  {
    "inputs": [
      {
        "internalType": "uint256",
        "name": "_campaignId",
        "type": "uint256"
      },
      {
        "internalType": "address[]",
        "name": "_tokens",
        "type": "address[]"
      },
      {
        "internalType": "uint256[]",
        "name": "_amounts",
        "type": "uint256[]"
      }
    ],
    "name": "setCampaignTokenAmountsFromV4",
    "outputs": [],
    "stateMutability": "nonpayable",
    "type": "function"
  },
  {
    "inputs": [
      {
        "internalType": "uint256",
        "name": "_campaignId",
        "type": "uint256"
      },
      {
        "internalType": "uint256",
        "name": "_minimumVoteAmount",
        "type": "uint256"
      },
      {
        "internalType": "uint256",
        "name": "_maximumVoteAmount",
        "type": "uint256"
      }
    ],
    "name": "setCampaignVoteLimits",
    "outputs": [],
    "stateMutability": "nonpayable",
    "type": "function"
  },
  {
    "inputs": [
      {
        "internalType": "uint256",
        "name": "_campaignId",
        "type": "uint256"
      },
      {
        "internalType": "string",
        "name": "_websiteUrl",
        "type": "string"
      }
    ],
    "name": "setCampaignWebsite",
    "outputs": [],
    "stateMutability": "nonpayable",
    "type": "function"
  },
  {
    "inputs": [
      {
        "internalType": "uint256",
        "name": "_nextId",
        "type": "uint256"
      }
    ],
    "name": "setNextCampaignId",
    "outputs": [],
    "stateMutability": "nonpayable",
    "type": "function"
  },
  {
    "inputs": [
      {
        "internalType": "uint256",
        "name": "_campaignId",
        "type": "uint256"
      },
      {
        "internalType": "address",
        "name": "_user",
        "type": "address"
      },
      {
        "internalType": "uint256",
        "name": "_maxAmount",
        "type": "uint256"
      }
    ],
    "name": "setUserMaxVoteAmount",
    "outputs": [],
    "stateMutability": "nonpayable",
    "type": "function"
  },
  {
    "inputs": [
      {
        "internalType": "uint256",
        "name": "_campaignId",
        "type": "uint256"
      },
      {
        "internalType": "address[]",
        "name": "_users",
        "type": "address[]"
      },
      {
        "internalType": "uint256[]",
        "name": "_maxAmounts",
        "type": "uint256[]"
      }
    ],
    "name": "setUserMaxVoteAmountsFromV4",
    "outputs": [],
    "stateMutability": "nonpayable",
    "type": "function"
  },
  {
    "inputs": [
      {
        "internalType": "uint256",
        "name": "_campaignId",
        "type": "uint256"
      },
      {
        "internalType": "string",
        "name": "_name",
        "type": "string"
      },
      {
        "internalType": "string",
        "name": "_description",
        "type": "string"
      },
      {
        "internalType": "uint256",
        "name": "_startTime",
        "type": "uint256"
      },
      {
        "internalType": "uint256",
        "name": "_endTime",
        "type": "uint256"
      },
      {
        "internalType": "uint256",
        "name": "_adminFeePercentage",
        "type": "uint256"
      },
      {
        "internalType": "uint256",
        "name": "_maxWinners",
        "type": "uint256"
      },
      {
        "internalType": "bool",
        "name": "_useQuadraticDistribution",
        "type": "bool"
      },
      {
        "internalType": "bool",
        "name": "_useCustomDistribution",
        "type": "bool"
      },
      {
        "internalType": "address",
        "name": "_payoutToken",
        "type": "address"
      }
    ],
    "name": "updateCampaign",
    "outputs": [],
    "stateMutability": "nonpayable",
    "type": "function"
  },
  {
    "inputs": [
      {
        "internalType": "uint256",
        "name": "_campaignId",
        "type": "uint256"
      },
      {
        "internalType": "string",
        "name": "_mainInfo",
        "type": "string"
      },
      {
        "internalType": "string",
        "name": "_additionalInfo",
        "type": "string"
      }
    ],
    "name": "updateCampaignMetadata",
    "outputs": [],
    "stateMutability": "nonpayable",
    "type": "function"
  },
  {
    "inputs": [
      {
        "internalType": "uint256",
        "name": "_campaignId",
        "type": "uint256"
      },
      {
        "internalType": "uint256",
        "name": "_participantCount",
        "type": "uint256"
      },
      {
        "internalType": "uint256",
        "name": "_projectCount",
        "type": "uint256"
      }
    ],
    "name": "updateCampaignStats",
    "outputs": [],
    "stateMutability": "nonpayable",
    "type": "function"
  },
  {
    "inputs": [
      {
        "internalType": "uint256",
        "name": "_campaignId",
        "type": "uint256"
      },
      {
        "internalType": "enum OfficialStatus",
        "name": "_newStatus",
        "type": "uint8"
      },
      {
        "internalType": "string",
        "name": "_reason",
        "type": "string"
      }
    ],
    "name": "updateCampaignStatus",
    "outputs": [],
    "stateMutability": "nonpayable",
    "type": "function"
  },
  {
    "inputs": [
      {
        "internalType": "uint256",
        "name": "_campaignId",
        "type": "uint256"
      },
      {
        "internalType": "address[]",
        "name": "_newTokens",
        "type": "address[]"
      },
      {
        "internalType": "uint256[]",
        "name": "_newWeights",
        "type": "uint256[]"
      }
    ],
    "name": "updateCampaignTokens",
    "outputs": [],
    "stateMutability": "nonpayable",
    "type": "function"
  },
  {
    "inputs": [
      {
        "internalType": "uint256",
        "name": "_campaignId",
        "type": "uint256"
      },
      {
        "internalType": "enum CampaignType",
        "name": "_newType",
        "type": "uint8"
      }
    ],
    "name": "updateCampaignType",
    "outputs": [],
    "stateMutability": "nonpayable",
    "type": "function"
  },
  {
    "inputs": [
      {
        "internalType": "uint256",
        "name": "_campaignId",
        "type": "uint256"
      },
      {
        "internalType": "string",
        "name": "_customDistributionData",
        "type": "string"
      }
    ],
    "name": "updateCustomDistributionData",
    "outputs": [],
    "stateMutability": "nonpayable",
    "type": "function"
  },
  {
    "inputs": [
      {
        "internalType": "uint256",
        "name": "_campaignId",
        "type": "uint256"
      },
      {
        "internalType": "address",
        "name": "_newToken",
        "type": "address"
      },
      {
        "internalType": "uint256",
        "name": "_newAmount",
        "type": "uint256"
      }
    ],
    "name": "updateProjectAdditionFee",
    "outputs": [],
    "stateMutability": "nonpayable",
    "type": "function"
  },
  {
    "inputs": [
      {
        "internalType": "uint256",
        "name": "_campaignId",
        "type": "uint256"
      },
      {
        "internalType": "address",
        "name": "_token",
        "type": "address"
      },
      {
        "internalType": "uint256",
        "name": "_newWeight",
        "type": "uint256"
      }
    ],
    "name": "updateTokenWeight",
    "outputs": [],
    "stateMutability": "nonpayable",
    "type": "function"
  }
]